norfab/__init__.py
norfab/clients/__init__.py
norfab/clients/picle_shell_client.py
norfab/clients/robot_client.py
norfab/clients/shell_clients/__init__.py
norfab/clients/shell_clients/agent/__init__.py
norfab/clients/shell_clients/agent/agent_picle_shell.py
norfab/clients/shell_clients/common.py
norfab/clients/shell_clients/containerlab/__init__.py
norfab/clients/shell_clients/containerlab/containerlab_deploy_netbox.py
norfab/clients/shell_clients/containerlab/containerlab_picle_shell.py
norfab/clients/shell_clients/fastapi/__init__.py
norfab/clients/shell_clients/fastapi/fastapi_picle_shell.py
norfab/clients/shell_clients/fastapi/fastapi_picle_shell_auth.py
norfab/clients/shell_clients/fastapi/fastapi_picle_shell_discover.py
norfab/clients/shell_clients/fastmcp/__init__.py
norfab/clients/shell_clients/fastmcp/fastmcp_picle_shell.py
norfab/clients/shell_clients/fastmcp/fastmcp_picle_shell_discover.py
norfab/clients/shell_clients/netbox/__init__.py
norfab/clients/shell_clients/netbox/netbox_picle_shell.py
norfab/clients/shell_clients/netbox/netbox_picle_shell_cache.py
norfab/clients/shell_clients/netbox/netbox_picle_shell_common.py
norfab/clients/shell_clients/netbox/netbox_picle_shell_create_device_interfaces.py
norfab/clients/shell_clients/netbox/netbox_picle_shell_create_ip.py
norfab/clients/shell_clients/netbox/netbox_picle_shell_create_ip_bulk.py
norfab/clients/shell_clients/netbox/netbox_picle_shell_create_prefix.py
norfab/clients/shell_clients/netbox/netbox_picle_shell_get_bgp_peerings.py
norfab/clients/shell_clients/netbox/netbox_picle_shell_get_circuits.py
norfab/clients/shell_clients/netbox/netbox_picle_shell_get_connections.py
norfab/clients/shell_clients/netbox/netbox_picle_shell_get_containerlab_inventory.py
norfab/clients/shell_clients/netbox/netbox_picle_shell_get_devices.py
norfab/clients/shell_clients/netbox/netbox_picle_shell_get_interfaces.py
norfab/clients/shell_clients/netbox/netbox_picle_shell_sync_device.py
norfab-0.15.2.dist-info/entry_points.txt
norfab-0.15.2.dist-info/licenses/LICENCE.txt
norfab-0.15.2.dist-info/METADATA
norfab-0.15.2.dist-info/WHEEL
norfab-0.15.2.dist-info/RECORD
