Metadata-Version: 2.4
Name: norfab
Version: 0.15.2
Summary: Network Automations Fabric [NorFab] - communication networks automations
License: Apache-2.0 license
License-File: LICENCE.txt
Keywords: Network,Automation,DevOps
Author: Denis Mulyalin
Author-email: d.mulyalin@gmail.com
Maintainer: Denis Mulyalin
Maintainer-email: d.mulyalin@gmail.com
Requires-Python: >=3.10,<=3.14
Classifier: License :: OSI Approved :: Apache Software License
Classifier: License :: Other/Proprietary License
Classifier: Operating System :: Microsoft :: Windows
Classifier: Operating System :: POSIX :: Linux
Classifier: Programming Language :: Python :: 3
Classifier: Programming Language :: Python :: 3.10
Classifier: Programming Language :: Python :: 3.11
Classifier: Programming Language :: Python :: 3.12
Classifier: Programming Language :: Python :: 3.13
Classifier: Programming Language :: Python :: 3.14
Classifier: Topic :: Utilities
Provides-Extra: agentservice
Provides-Extra: docs
Provides-Extra: fastapiservice
Provides-Extra: fastmcpservice
Provides-Extra: full
Provides-Extra: netboxservice
Provides-Extra: nfcli
Provides-Extra: nornirservice
Provides-Extra: robot
Requires-Dist: N2G (==0.3.3) ; extra == "nornirservice" or extra == "full"
Requires-Dist: cerberus (==1.3.5) ; extra == "nornirservice" or extra == "full"
Requires-Dist: diskcache (==5.6.3) ; extra == "netboxservice" or extra == "fastapiservice" or extra == "full"
Requires-Dist: dnspython (==2.4.2) ; extra == "nornirservice" or extra == "full"
Requires-Dist: fastapi[standard] (==0.116.1) ; extra == "fastapiservice" or extra == "full"
Requires-Dist: jinja2 (==3.1.6)
Requires-Dist: jmespath (==1.0.1) ; extra == "nornirservice" or extra == "full"
Requires-Dist: langchain (==1.0.2) ; extra == "agentservice" or extra == "full"
Requires-Dist: langchain-community (==0.4.1) ; extra == "agentservice" or extra == "full"
Requires-Dist: langchain-ollama (==1.0.0) ; extra == "agentservice" or extra == "full"
Requires-Dist: lxml (==4.9.4) ; extra == "nornirservice" or extra == "full"
Requires-Dist: mcp (>=1.13.0) ; (python_version >= "3.10" and python_version < "3.12") and (extra == "fastmcpservice" or extra == "full")
Requires-Dist: mdutils (==1.8.1)
Requires-Dist: mkdocs ; extra == "docs"
Requires-Dist: mkdocs-material ; extra == "docs"
Requires-Dist: mkdocs-material-extensions ; extra == "docs"
Requires-Dist: mkdocstrings[python] ; extra == "docs"
Requires-Dist: napalm (==5.1.0) ; extra == "nornirservice" or extra == "full"
Requires-Dist: ncclient (==0.6.15) ; extra == "nornirservice" or extra == "full"
Requires-Dist: netmiko (==4.6.0) ; extra == "nornirservice" or extra == "full"
Requires-Dist: nornir (==3.5.0) ; extra == "nornirservice" or extra == "full"
Requires-Dist: nornir-napalm (==0.5.0) ; extra == "nornirservice" or extra == "full"
Requires-Dist: nornir-netmiko (==1.0.1) ; extra == "nornirservice" or extra == "full"
Requires-Dist: nornir-salt (==0.23.*) ; extra == "nfcli" or extra == "nornirservice" or extra == "full"
Requires-Dist: nornir-scrapli (==2025.01.30) ; extra == "nornirservice" or extra == "full"
Requires-Dist: ntc-templates (==8.0.0) ; extra == "nornirservice" or extra == "full"
Requires-Dist: ollama (==0.6.0) ; extra == "agentservice" or extra == "full"
Requires-Dist: paramiko (==4.0.0) ; extra == "nornirservice" or extra == "full"
Requires-Dist: picle (==0.9.3) ; extra == "nfcli" or extra == "full"
Requires-Dist: psutil (==7.0.0)
Requires-Dist: puresnmp[crypto] (==2.0.0) ; extra == "nornirservice" or extra == "full"
Requires-Dist: pydantic (==2.11.7) ; extra == "nfcli" or extra == "nornirservice" or extra == "full" or extra == "full"
Requires-Dist: pygments ; extra == "docs"
Requires-Dist: pygnmi (==0.8.15) ; extra == "nornirservice" or extra == "full"
Requires-Dist: pymdown-extensions ; extra == "docs"
Requires-Dist: pynetbox (==7.5.0) ; extra == "netboxservice" or extra == "full"
Requires-Dist: pyreadline3 (==3.4.1) ; extra == "nfcli"
Requires-Dist: python-multipart (==0.0.20) ; extra == "fastapiservice" or extra == "full"
Requires-Dist: pythonping (==1.1.4) ; extra == "nornirservice" or extra == "full"
Requires-Dist: pyyaml (==6.0.2)
Requires-Dist: pyzmq (==27.0.2)
Requires-Dist: requests (==2.32.5) ; extra == "nornirservice" or extra == "netboxservice" or extra == "full" or extra == "full"
Requires-Dist: rich (==14.1.0) ; extra == "nfcli" or extra == "full"
Requires-Dist: robotframework (==7.3.2) ; extra == "full"
Requires-Dist: scrapli (==2025.01.30) ; extra == "nornirservice" or extra == "full"
Requires-Dist: scrapli-community (==2025.01.30) ; extra == "nornirservice" or extra == "full"
Requires-Dist: scrapli-netconf (==2025.01.30) ; extra == "nornirservice" or extra == "full"
Requires-Dist: tabulate (==0.9.0) ; extra == "nfcli" or extra == "nornirservice" or extra == "full" or extra == "full"
Requires-Dist: textfsm (==1.1.3) ; extra == "nornirservice" or extra == "full"
Requires-Dist: tornado (==6.5.2)
Requires-Dist: ttp (==0.10.0) ; extra == "nornirservice" or extra == "full"
Requires-Dist: ttp-templates (==0.3.*) ; extra == "nornirservice" or extra == "full"
Requires-Dist: uvicorn (==0.35.0) ; extra == "fastapiservice" or extra == "full"
Requires-Dist: xmltodict (==0.13.0) ; extra == "nornirservice" or extra == "full"
Project-URL: Documentation, https://docs.norfablabs.com
Project-URL: Homepage, https://github.com/norfablabs/NORFAB
Project-URL: Repository, https://github.com/norfablabs/NORFAB
